resutil/__init__.py
resutil/config_file.py
resutil/core.py
resutil/ex_dir.py
resutil/exp_file.py
resutil/git.py
resutil/main.py
resutil/utils.py
resutil/cli/__init__.py
resutil/cli/__main__.py
resutil/cli/cli_main.py
resutil/storage/__init__.py
resutil/storage/storage.py
resutil/storage/gcs/gcs.py
resutil/storage/gdrive/gdrive.py
resutil-0.1.20.dist-info/METADATA
resutil-0.1.20.dist-info/WHEEL
resutil-0.1.20.dist-info/entry_points.txt
resutil-0.1.20.dist-info/licenses/LICENSE
resutil-0.1.20.dist-info/RECORD
