Metadata-Version: 2.4
Name: resutil
Version: 0.1.20
Summary: Resutil is a utility to manage experimental result data obtained from Python projects. It also manages dependency such as codes and input data with result data. Data is synced to the cloud for team sharing and collaboration.
Project-URL: Homepage, https://github.com/KatayamaLab/resutil
Project-URL: Issues, https://github.com/KatayamaLab/resutil/issues
Author-email: nobkat <katayama@rs.tus.ac.jp>
License: MIT License
License-File: LICENSE
Requires-Python: >=3.8
Requires-Dist: gitpython>=3.1.0
Requires-Dist: google-api-python-client>=2.133.0
Requires-Dist: google-auth-httplib2>=0.2.0
Requires-Dist: google-auth-oauthlib>=1.2.0
Requires-Dist: google-auth>=2.30.0
Requires-Dist: google-cloud-storage>=2.17.0
Requires-Dist: prompt-toolkit>=3.0.47
Requires-Dist: pyreadline3>=3.5.4; platform_system == 'Windows'
Requires-Dist: pytest-mock>=3.14.0
Requires-Dist: pyyaml>=6.0.0
Requires-Dist: rich>=13.7.0
